toolbox/__init__.py
toolbox/config.py
toolbox/library.py
toolbox/toolbox.py
validatortoolbox-1.9.1.dist-info/LICENSE
validatortoolbox-1.9.1.dist-info/METADATA
validatortoolbox-1.9.1.dist-info/WHEEL
validatortoolbox-1.9.1.dist-info/top_level.txt
validatortoolbox-1.9.1.dist-info/RECORD
