Metadata-Version: 2.1
Name: validatortoolbox
Version: 1.9.1
Summary: Harmony ONE Validator Node Toolbox and Easy Setup
Home-page: https://github.com/easy-node-pro/validatortoolbox
Author: EasyNode.PRO
Author-email: support@easynode.pro
Project-URL: Bug Tracker, https://github.com/easy-node-pro/validatortoolbox/issues
Project-URL: repository, https://github.com/easy-node-pro/validatortoolbox
Classifier: Programming Language :: Python :: 3
Classifier: License :: OSI Approved :: MIT License
Classifier: Operating System :: OS Independent
Requires-Python: >=3.6
License-File: LICENSE
